{
    "Mangroves": {
        "f1-score": 0.8577190230786467,
        "precision": 0.8668478260869565,
        "recall": 0.848780487804878,
        "support": 2255
    },
    "Mangroves > Not Mangroves": {
        "f1-score": 0.6051660516605166,
        "precision": 0.5347826086956522,
        "recall": 0.6968838526912181,
        "support": 353
    },
    "Not Mangroves": {
        "f1-score": 0.9538001041124413,
        "precision": 0.966376582278481,
        "recall": 0.9415467625899281,
        "support": 7784
    },
    "Not Mangroves > Mangroves": {
        "f1-score": 0.377906976744186,
        "precision": 0.26859504132231404,
        "recall": 0.6372549019607843,
        "support": 102
    },
    "accuracy": 0.9104250047646274,
    "accuracy_conf_interval": [
        0.004571816635033982,
        0.005463878417479638,
        0.0064953248534324265,
        0.007192248120968095
    ],
    "cls_confidence_intervals": {
        "Mangroves": [
            0.01185741107654128,
            0.014171052262207872,
            0.01684619988313487,
            0.018653732059436896
        ],
        "Mangroves > Not Mangroves": [
            0.038140074826877125,
            0.045582040646755584,
            0.054186813625990066,
            0.06000084942277011
        ],
        "Not Mangroves": [
            0.003394601608065852,
            0.004056962897444555,
            0.00482281813828868,
            0.005340287895615792
        ],
        "Not Mangroves > Mangroves": [
            0.046726592390664866,
            0.05584397627177021,
            0.06638595138429826,
            0.0735089075414118
        ]
    },
    "cohen_kappa": 0.7852028639618138,
    "confusion_matrix": [
        [
            1914,
            67,
            199,
            75
        ],
        [
            63,
            246,
            44,
            0
        ],
        [
            206,
            147,
            7329,
            102
        ],
        [
            25,
            0,
            12,
            65
        ]
    ],
    "macro avg": {
        "f1-score": 0.6986480388989477,
        "precision": 0.659150514595851,
        "recall": 0.7811165012617022,
        "support": 10494
    },
    "producer_accuracy": [
        86.68478260869566,
        53.47826086956522,
        96.6376582278481,
        26.859504132231404
    ],
    "user_accuracy": [
        84.8780487804878,
        69.68838526912181,
        94.15467625899281,
        63.725490196078425
    ],
    "weighted avg": {
        "f1-score": 0.9158287150102592,
        "precision": 0.923688976497639,
        "recall": 0.9104250047646274,
        "support": 10494
    }
}