{
    "Mangroves": {
        "f1-score": 0.8560202076901486,
        "precision": 0.8804849884526559,
        "recall": 0.8328782086291644,
        "support": 1831
    },
    "Mangroves > Not Mangroves": {
        "f1-score": 0.5562130177514792,
        "precision": 0.45965770171149145,
        "recall": 0.704119850187266,
        "support": 267
    },
    "Not Mangroves": {
        "f1-score": 0.9449778053060803,
        "precision": 0.9541380029184907,
        "recall": 0.9359918200408998,
        "support": 4890
    },
    "Not Mangroves > Mangroves": {
        "f1-score": 0.5609756097560974,
        "precision": 0.48677248677248675,
        "recall": 0.6618705035971223,
        "support": 139
    },
    "accuracy": 0.8954679388241897,
    "accuracy_conf_interval": [
        0.005943472343388397,
        0.007103174264049547,
        0.008444079609814003,
        0.009350096735330526
    ],
    "cls_confidence_intervals": {
        "Mangroves": [
            0.012783274391346706,
            0.015277571833560698,
            0.018161603251120626,
            0.020110273127850308
        ],
        "Mangroves > Not Mangroves": [
            0.04041419638570602,
            0.04829989324145354,
            0.05741773023091161,
            0.06357843089946436
        ],
        "Not Mangroves": [
            0.004953259338251748,
            0.005919748965227699,
            0.007037252596418643,
            0.007792322617493604
        ],
        "Not Mangroves > Mangroves": [
            0.059625347423752716,
            0.07125956155521666,
            0.08471162164472185,
            0.09380085143492806
        ]
    },
    "cohen_kappa": 0.7790425423052894,
    "confusion_matrix": [
        [
            1525,
            105,
            160,
            41
        ],
        [
            47,
            188,
            32,
            0
        ],
        [
            141,
            116,
            4577,
            56
        ],
        [
            19,
            0,
            28,
            92
        ]
    ],
    "macro avg": {
        "f1-score": 0.7295466601259515,
        "precision": 0.6952632949637811,
        "recall": 0.7837150956136131,
        "support": 7127
    },
    "producer_accuracy": [
        88.04849884526558,
        45.965770171149146,
        95.41380029184907,
        48.67724867724868
    ],
    "user_accuracy": [
        83.28782086291643,
        70.4119850187266,
        93.59918200408998,
        66.18705035971223
    ],
    "weighted avg": {
        "f1-score": 0.9000700089410885,
        "precision": 0.9075758145287746,
        "recall": 0.8954679388241897,
        "support": 7127
    }
}