{
    "Mangrove": {
        "f1-score": 0.9598393574297188,
        "precision": 0.952191235059761,
        "recall": 0.9676113360323887,
        "support": 494
    },
    "Other": {
        "f1-score": 0.9601593625498008,
        "precision": 0.9678714859437751,
        "recall": 0.9525691699604744,
        "support": 506
    },
    "accuracy": 0.96,
    "accuracy_conf_interval": [
        0.010162708300448266,
        0.012145675773706465,
        0.014438481914661258,
        0.015987675253144224
    ],
    "cls_confidence_intervals": {
        "Mangrove": [
            0.015617367912659382,
            0.018664659212690483,
            0.02218808977835144,
            0.024568786106500737
        ],
        "Other": [
            0.012959353733344132,
            0.015488008120338109,
            0.018411764755299896,
            0.02038727599513894
        ]
    },
    "cohen_kappa": 0.9200038398156889,
    "confusion_matrix": [
        [
            478,
            16
        ],
        [
            24,
            482
        ]
    ],
    "macro avg": {
        "f1-score": 0.9599993599897598,
        "precision": 0.9600313605017681,
        "recall": 0.9600902529964315,
        "support": 1000
    },
    "producer_accuracy": [
        95.2191235059761,
        96.78714859437751
    ],
    "user_accuracy": [
        96.76113360323887,
        95.25691699604744
    ],
    "weighted avg": {
        "f1-score": 0.9600012800204802,
        "precision": 0.9601254420070722,
        "recall": 0.96,
        "support": 1000
    }
}