{
    "Mangrove": {
        "f1-score": 0.8851224105461394,
        "precision": 0.8362989323843416,
        "recall": 0.94,
        "support": 250
    },
    "Other": {
        "f1-score": 0.9088191330343797,
        "precision": 0.9529780564263323,
        "recall": 0.8685714285714285,
        "support": 350
    },
    "accuracy": 0.8983333333333333,
    "accuracy_conf_interval": [
        0.02023374500771019,
        0.02418179281409267,
        0.028746723090222408,
        0.03183113543895872
    ],
    "cls_confidence_intervals": {
        "Mangrove": [
            0.036199053501925434,
            0.04326228345352064,
            0.0514291430850526,
            0.05694729148473636
        ],
        "Other": [
            0.01943749276839105,
            0.02323017428417467,
            0.02761546228679948,
            0.030578494721005434
        ]
    },
    "cohen_kappa": 0.7944974733295901,
    "confusion_matrix": [
        [
            235,
            15
        ],
        [
            46,
            304
        ]
    ],
    "macro avg": {
        "f1-score": 0.8969707717902595,
        "precision": 0.8946384944053369,
        "recall": 0.9042857142857142,
        "support": 600
    },
    "producer_accuracy": [
        83.62989323843416,
        95.29780564263322
    ],
    "user_accuracy": [
        94.0,
        86.85714285714286
    ],
    "weighted avg": {
        "f1-score": 0.8989454986642795,
        "precision": 0.9043617547421695,
        "recall": 0.8983333333333333,
        "support": 600
    }
}